<problem display_name="Multiple Choice" markdown="&gt;&gt;1. A synchronous motor is a useful industrial machine on account of which of the following reasons ? I. It improves the power factor of the complete installation II. Its speed is constant at all loads, provided mains frequency remains constant III. It can always be adjusted to operate at unity power factor for optimum efficiency and economy.&lt;&lt;&#10;( ) I only&#10;( ) II only&#10;( ) III only&#10;(x) I, II and III.&#10;&#10;&gt;&gt;2) In a synchronous motor if the back emf generated in the armature at no load is approximately equal to the applied voltage, then&lt;&lt;&#10;( ) the torque generated is maximum&#10;( ) the excitation is said to be zero percent&#10;(x) the excitation is said to be 100%&#10;( ) the motor is said to be fully loaded&#10;&#10;&gt;&gt;3) A synchronous motor working on leading power factor and not driving any mechanical, is known&lt;&lt;&#10;(x) synchronous condenser&#10;( ) spinning motor&#10;( ) synchronous induction motor&#10;( ) none of the above&#10;&#10;&gt;&gt;4) The constant speed of a synchronous motor can be changed to new fixed value by&lt;&lt;&#10;( ) changing the applied voltage&#10;( ) interchanging any two phases&#10;( ) changing the load&#10;(x) changing the frequency of supply.&#10;&#10;&gt;&gt;5) A synchronous machine has its field winding on the stator and armature winding on the rotor. Under steady running conditions, the air-gap field&lt;&lt;&#10;( ) rotates at synchronous speed with direction of rotation of the rotor&#10;(x) remains stationary with respect to stator&#10;( ) remains stationary with respect to rotor.&#10;( ) rotates at synchronous speed with respect to stator">
<p>1. A synchronous motor is a useful industrial machine on account of which of the following reasons ? I. It improves the power factor of the complete installation II. Its speed is constant at all loads, provided mains frequency remains constant III. It can always be adjusted to operate at unity power factor for optimum efficiency and economy.</p>
<multiplechoiceresponse>
  <choicegroup label="1. A synchronous motor is a useful industrial machine on account of which of the following reasons ? I. It improves the power factor of the complete installation II. Its speed is constant at all loads, provided mains frequency remains constant III. It can always be adjusted to operate at unity power factor for optimum efficiency and economy." type="MultipleChoice">
    <choice correct="false">I only</choice>
    <choice correct="false">II only</choice>
    <choice correct="false">III only</choice>
    <choice correct="true">I, II and III.</choice>
  </choicegroup>
</multiplechoiceresponse>

<p>2) In a synchronous motor if the back emf generated in the armature at no load is approximately equal to the applied voltage, then</p>
<multiplechoiceresponse>
  <choicegroup label="2) In a synchronous motor if the back emf generated in the armature at no load is approximately equal to the applied voltage, then" type="MultipleChoice">
    <choice correct="false">the torque generated is maximum</choice>
    <choice correct="false">the excitation is said to be zero percent</choice>
    <choice correct="true">the excitation is said to be 100%</choice>
    <choice correct="false">the motor is said to be fully loaded</choice>
  </choicegroup>
</multiplechoiceresponse>

<p>3) A synchronous motor working on leading power factor and not driving any mechanical, is known</p>
<multiplechoiceresponse>
  <choicegroup label="3) A synchronous motor working on leading power factor and not driving any mechanical, is known" type="MultipleChoice">
    <choice correct="true">synchronous condenser</choice>
    <choice correct="false">spinning motor</choice>
    <choice correct="false">synchronous induction motor</choice>
    <choice correct="false">none of the above</choice>
  </choicegroup>
</multiplechoiceresponse>

<p>4) The constant speed of a synchronous motor can be changed to new fixed value by</p>
<multiplechoiceresponse>
  <choicegroup label="4) The constant speed of a synchronous motor can be changed to new fixed value by" type="MultipleChoice">
    <choice correct="false">changing the applied voltage</choice>
    <choice correct="false">interchanging any two phases</choice>
    <choice correct="false">changing the load</choice>
    <choice correct="true">changing the frequency of supply.</choice>
  </choicegroup>
</multiplechoiceresponse>

<p>5) A synchronous machine has its field winding on the stator and armature winding on the rotor. Under steady running conditions, the air-gap field</p>
<multiplechoiceresponse>
  <choicegroup label="5) A synchronous machine has its field winding on the stator and armature winding on the rotor. Under steady running conditions, the air-gap field" type="MultipleChoice">
    <choice correct="false">rotates at synchronous speed with direction of rotation of the rotor</choice>
    <choice correct="true">remains stationary with respect to stator</choice>
    <choice correct="false">remains stationary with respect to rotor.</choice>
    <choice correct="false">rotates at synchronous speed with respect to stator</choice>
  </choicegroup>
</multiplechoiceresponse>


</problem>
